asaplib/__init__.py
asaplib/config.py
asaplib/cli/__init__.py
asaplib/cli/bck_cmd_asap.py
asaplib/cli/cmd_asap.py
asaplib/cli/cmd_asap_gen_desc.py
asaplib/cli/cmd_cli_options.py
asaplib/cli/func_asap.py
asaplib/cluster/__init__.py
asaplib/cluster/ml_cluster_base.py
asaplib/cluster/ml_cluster_fit.py
asaplib/cluster/ml_cluster_tools.py
asaplib/compressor/__init__.py
asaplib/compressor/cur.py
asaplib/compressor/fps.py
asaplib/compressor/reweight.py
asaplib/compressor/sparsifier.py
asaplib/compressor/split.py
asaplib/data/__init__.py
asaplib/data/design_matrix.py
asaplib/data/xyz.py
asaplib/descriptors/__init__.py
asaplib/descriptors/atomic_descriptors.py
asaplib/descriptors/atomic_to_global.py
asaplib/descriptors/global_descriptors.py
asaplib/fit/__init__.py
asaplib/fit/base.py
asaplib/fit/getscore.py
asaplib/fit/krr.py
asaplib/fit/ridgeregression.py
asaplib/fit/sparse_krr.py
asaplib/fit/sparse_krr_wrapper.py
asaplib/hypers/__init__.py
asaplib/hypers/hyper_acsf.py
asaplib/hypers/hyper_soap.py
asaplib/hypers/symfun_gen.py
asaplib/hypers/test.py
asaplib/hypers/univeral_length_scales.py
asaplib/io/__init__.py
asaplib/io/cscope.py
asaplib/io/io_cell.py
asaplib/io/io_parse.py
asaplib/kde/__init__.py
asaplib/kde/density_estimation.py
asaplib/kde/density_estimation_internal.py
asaplib/kde/ml_density_estimation.py
asaplib/kernel/__init__.py
asaplib/kernel/kernel_transforms.py
asaplib/kernel/ml_kernel_operations.py
asaplib/plot/__init__.py
asaplib/plot/plot_colors.py
asaplib/plot/plot_styles.py
asaplib/plot/plotters.py
asaplib/reducedim/__init__.py
asaplib/reducedim/dim_reducer.py
asaplib/reducedim/ml_kpca.py
asaplib/reducedim/ml_pca.py
asaplib/reducedim/sparse_kpca.py
asaplib/util/__init__.py
asaplib/util/util_fft.py
asaplib/util/util_gettcv.py
asaplib-0.0.2.dist-info/LICENSE
asaplib-0.0.2.dist-info/METADATA
asaplib-0.0.2.dist-info/WHEEL
asaplib-0.0.2.dist-info/entry_points.txt
asaplib-0.0.2.dist-info/top_level.txt
asaplib-0.0.2.dist-info/RECORD
