Metadata-Version: 2.1
Name: asaplib
Version: 0.0.2
Summary: Automatic Selection And Prediction tools for materials and molecules
Home-page: https://github.com/BingqingCheng/ASAP
Author: Bingqing Cheng
Author-email: tonicbq@gmail.com
License: UNKNOWN
Platform: UNKNOWN
Classifier: Programming Language :: Python :: 3
Classifier: License :: OSI Approved :: MIT License
Classifier: Operating System :: OS Independent
Requires-Python: >=3.6
Requires-Dist: dscribe (>=0.4.0)
Requires-Dist: click (>=7.0)
Requires-Dist: numpy
Requires-Dist: scipy
Requires-Dist: scikit-learn
Requires-Dist: ase (>=3.19.1)
Requires-Dist: umap-learn
Requires-Dist: PyYAML
Requires-Dist: tqdm (>=4.46.1)
Requires-Dist: pandas
Provides-Extra: testing
Requires-Dist: pytest (>=5.0) ; extra == 'testing'
